[{"OBJECT_NAME":"ISS (ZARYA)","OBJECT_ID":"1998-067A","EPOCH":"2026-04-11T22:35:02.626368","MEAN_MOTION":15.4887769,"ECCENTRICITY":0.00064516,"INCLINATION":51.6326,"RA_OF_ASC_NODE":267.9482,"ARG_OF_PERICENTER":301.5882,"MEAN_ANOMALY":58.4476,"EPHEMERIS_TYPE":0,"CLASSIFICATION_TYPE":"U","NORAD_CAT_ID":25544,"ELEMENT_SET_NO":999,"REV_AT_EPOCH":56148,"BSTAR":0.00010656761,"MEAN_MOTION_DOT":5.402e-5,"MEAN_MOTION_DDOT":0},{"OBJECT_NAME":"POISK","OBJECT_ID":"2009-060A","EPOCH":"2026-04-11T22:35:02.626368","MEAN_MOTION":15.4887769,"ECCENTRICITY":0.00064516,"INCLINATION":51.6326,"RA_OF_ASC_NODE":267.9482,"ARG_OF_PERICENTER":301.5882,"MEAN_ANOMALY":58.4476,"EPHEMERIS_TYPE":0,"CLASSIFICATION_TYPE":"U","NORAD_CAT_ID":36086,"ELEMENT_SET_NO":999,"REV_AT_EPOCH":56057,"BSTAR":0.00010656761,"MEAN_MOTION_DOT":5.402e-5,"MEAN_MOTION_DDOT":0},{"OBJECT_NAME":"CSS (TIANHE)","OBJECT_ID":"2021-035A","EPOCH":"2026-04-12T03:57:55.171296","MEAN_MOTION":15.62300157,"ECCENTRICITY":0.00049717,"INCLINATION":41.4686,"RA_OF_ASC_NODE":4.2206,"ARG_OF_PERICENTER":190.5766,"MEAN_ANOMALY":169.497,"EPHEMERIS_TYPE":0,"CLASSIFICATION_TYPE":"U","NORAD_CAT_ID":48274,"ELEMENT_SET_NO":999,"REV_AT_EPOCH":28284,"BSTAR":0.00020763917,"MEAN_MOTION_DOT":0.00018582,"MEAN_MOTION_DDOT":0},{"OBJECT_NAME":"ISS (NAUKA)","OBJECT_ID":"2021-066A","EPOCH":"2026-04-11T22:35:02.626368","MEAN_MOTION":15.4887769,"ECCENTRICITY":0.00064516,"INCLINATION":51.6326,"RA_OF_ASC_NODE":267.9482,"ARG_OF_PERICENTER":301.5882,"MEAN_ANOMALY":58.4476,"EPHEMERIS_TYPE":0,"CLASSIFICATION_TYPE":"U","NORAD_CAT_ID":49044,"ELEMENT_SET_NO":999,"REV_AT_EPOCH":56061,"BSTAR":0.00010656761,"MEAN_MOTION_DOT":5.402e-5,"MEAN_MOTION_DDOT":0},{"OBJECT_NAME":"FREGAT DEB","OBJECT_ID":"2011-037PF","EPOCH":"2026-04-10T23:43:52.229280","MEAN_MOTION":12.40984828,"ECCENTRICITY":0.09507887,"INCLINATION":51.6392,"RA_OF_ASC_NODE":203.7553,"ARG_OF_PERICENTER":133.4539,"MEAN_ANOMALY":234.9499,"EPHEMERIS_TYPE":0,"CLASSIFICATION_TYPE":"U","NORAD_CAT_ID":49271,"ELEMENT_SET_NO":999,"REV_AT_EPOCH":21670,"BSTAR":0.005693483,"MEAN_MOTION_DOT":3.799e-5,"MEAN_MOTION_DDOT":0},{"OBJECT_NAME":"CSS (WENTIAN)","OBJECT_ID":"2022-085A","EPOCH":"2026-04-12T03:57:55.171296","MEAN_MOTION":15.62300157,"ECCENTRICITY":0.00049717,"INCLINATION":41.4686,"RA_OF_ASC_NODE":4.2206,"ARG_OF_PERICENTER":190.5766,"MEAN_ANOMALY":169.497,"EPHEMERIS_TYPE":0,"CLASSIFICATION_TYPE":"U","NORAD_CAT_ID":53239,"ELEMENT_SET_NO":999,"REV_AT_EPOCH":28313,"BSTAR":0.00020763917,"MEAN_MOTION_DOT":0.00018582,"MEAN_MOTION_DDOT":0},{"OBJECT_NAME":"CSS (MENGTIAN)","OBJECT_ID":"2022-143A","EPOCH":"2026-04-12T03:57:55.171296","MEAN_MOTION":15.62300157,"ECCENTRICITY":0.00049717,"INCLINATION":41.4686,"RA_OF_ASC_NODE":4.2206,"ARG_OF_PERICENTER":190.5766,"MEAN_ANOMALY":169.497,"EPHEMERIS_TYPE":0,"CLASSIFICATION_TYPE":"U","NORAD_CAT_ID":54216,"ELEMENT_SET_NO":999,"REV_AT_EPOCH":28327,"BSTAR":0.00020763917,"MEAN_MOTION_DOT":0.00018582,"MEAN_MOTION_DDOT":0},{"OBJECT_NAME":"TIANZHOU-9","OBJECT_ID":"2025-149A","EPOCH":"2026-04-12T03:57:55.171296","MEAN_MOTION":15.62300157,"ECCENTRICITY":0.00049717,"INCLINATION":41.4686,"RA_OF_ASC_NODE":4.2206,"ARG_OF_PERICENTER":190.5766,"MEAN_ANOMALY":169.497,"EPHEMERIS_TYPE":0,"CLASSIFICATION_TYPE":"U","NORAD_CAT_ID":64786,"ELEMENT_SET_NO":999,"REV_AT_EPOCH":28327,"BSTAR":0.00020763917,"MEAN_MOTION_DOT":0.00018582,"MEAN_MOTION_DDOT":0},{"OBJECT_NAME":"PROGRESS-MS 32","OBJECT_ID":"2025-204A","EPOCH":"2026-04-11T22:35:02.626368","MEAN_MOTION":15.4887769,"ECCENTRICITY":0.00064516,"INCLINATION":51.6326,"RA_OF_ASC_NODE":267.9482,"ARG_OF_PERICENTER":301.5882,"MEAN_ANOMALY":58.4476,"EPHEMERIS_TYPE":0,"CLASSIFICATION_TYPE":"U","NORAD_CAT_ID":65586,"ELEMENT_SET_NO":999,"REV_AT_EPOCH":55450,"BSTAR":0.00010656761,"MEAN_MOTION_DOT":5.402e-5,"MEAN_MOTION_DDOT":0},{"OBJECT_NAME":"YOTSUBA-KULOVER","OBJECT_ID":"1998-067XN","EPOCH":"2026-04-12T02:31:27.685920","MEAN_MOTION":16.12585561,"ECCENTRICITY":0.00113479,"INCLINATION":51.6093,"RA_OF_ASC_NODE":241.0715,"ARG_OF_PERICENTER":312.3245,"MEAN_ANOMALY":47.6808,"EPHEMERIS_TYPE":0,"CLASSIFICATION_TYPE":"U","NORAD_CAT_ID":65941,"ELEMENT_SET_NO":999,"REV_AT_EPOCH":2882,"BSTAR":0.0011899863,"MEAN_MOTION_DOT":0.01359606,"MEAN_MOTION_DDOT":0.0013034139},{"OBJECT_NAME":"BOTAN","OBJECT_ID":"1998-067XQ","EPOCH":"2026-04-12T06:10:42.283776","MEAN_MOTION":16.08772397,"ECCENTRICITY":0.00114308,"INCLINATION":51.6144,"RA_OF_ASC_NODE":240.6256,"ARG_OF_PERICENTER":310.7999,"MEAN_ANOMALY":49.2022,"EPHEMERIS_TYPE":0,"CLASSIFICATION_TYPE":"U","NORAD_CAT_ID":65943,"ELEMENT_SET_NO":999,"REV_AT_EPOCH":2884,"BSTAR":0.00099149551,"MEAN_MOTION_DOT":0.00890593,"MEAN_MOTION_DDOT":0.00044878091},{"OBJECT_NAME":"HRC MONOBLOCK CAMERA","OBJECT_ID":"1998-067XR","EPOCH":"2026-04-11T20:40:10.168320","MEAN_MOTION":15.66040109,"ECCENTRICITY":0.00039387,"INCLINATION":51.6264,"RA_OF_ASC_NODE":257.6564,"ARG_OF_PERICENTER":263.8081,"MEAN_ANOMALY":96.2466,"EPHEMERIS_TYPE":0,"CLASSIFICATION_TYPE":"U","NORAD_CAT_ID":66052,"ELEMENT_SET_NO":999,"REV_AT_EPOCH":2758,"BSTAR":0.00045050874,"MEAN_MOTION_DOT":0.00046776,"MEAN_MOTION_DDOT":0},{"OBJECT_NAME":"HTV-X1","OBJECT_ID":"2025-241A","EPOCH":"2026-04-11T21:47:03.293664","MEAN_MOTION":15.32622094,"ECCENTRICITY":0.000741,"INCLINATION":51.6358,"RA_OF_ASC_NODE":272.9032,"ARG_OF_PERICENTER":302.2344,"MEAN_ANOMALY":57.7919,"EPHEMERIS_TYPE":0,"CLASSIFICATION_TYPE":"U","NORAD_CAT_ID":66174,"ELEMENT_SET_NO":999,"REV_AT_EPOCH":2603,"BSTAR":0.00016903,"MEAN_MOTION_DOT":5.039e-5,"MEAN_MOTION_DDOT":0},{"OBJECT_NAME":"SZ-21 MODULE","OBJECT_ID":"2025-246C","EPOCH":"2026-04-12T02:08:31.842816","MEAN_MOTION":15.7131613,"ECCENTRICITY":0.00042948,"INCLINATION":41.475,"RA_OF_ASC_NODE":357.3447,"ARG_OF_PERICENTER":260.2724,"MEAN_ANOMALY":99.7634,"EPHEMERIS_TYPE":0,"CLASSIFICATION_TYPE":"U","NORAD_CAT_ID":66515,"ELEMENT_SET_NO":999,"REV_AT_EPOCH":2332,"BSTAR":0.00024644966,"MEAN_MOTION_DOT":0.00032051,"MEAN_MOTION_DDOT":0},{"OBJECT_NAME":"SHENZHOU-22","OBJECT_ID":"2025-272A","EPOCH":"2026-04-12T03:57:55.171296","MEAN_MOTION":15.62300157,"ECCENTRICITY":0.00049717,"INCLINATION":41.4686,"RA_OF_ASC_NODE":4.2206,"ARG_OF_PERICENTER":190.5766,"MEAN_ANOMALY":169.497,"EPHEMERIS_TYPE":0,"CLASSIFICATION_TYPE":"U","NORAD_CAT_ID":66645,"ELEMENT_SET_NO":999,"REV_AT_EPOCH":28327,"BSTAR":0.00020763917,"MEAN_MOTION_DOT":0.00018582,"MEAN_MOTION_DDOT":0},{"OBJECT_NAME":"SOYUZ-MS 28","OBJECT_ID":"2025-275A","EPOCH":"2026-04-11T22:35:02.626368","MEAN_MOTION":15.4887769,"ECCENTRICITY":0.00064516,"INCLINATION":51.6326,"RA_OF_ASC_NODE":267.9482,"ARG_OF_PERICENTER":301.5882,"MEAN_ANOMALY":58.4476,"EPHEMERIS_TYPE":0,"CLASSIFICATION_TYPE":"U","NORAD_CAT_ID":66664,"ELEMENT_SET_NO":999,"REV_AT_EPOCH":56085,"BSTAR":0.00010656761,"MEAN_MOTION_DOT":5.402e-5,"MEAN_MOTION_DDOT":0},{"OBJECT_NAME":"DUPLEX","OBJECT_ID":"1998-067XS","EPOCH":"2026-04-12T03:31:27.402816","MEAN_MOTION":15.58481878,"ECCENTRICITY":0.00037325,"INCLINATION":51.6279,"RA_OF_ASC_NODE":261.823,"ARG_OF_PERICENTER":278.147,"MEAN_ANOMALY":81.9099,"EPHEMERIS_TYPE":0,"CLASSIFICATION_TYPE":"U","NORAD_CAT_ID":66906,"ELEMENT_SET_NO":999,"REV_AT_EPOCH":2034,"BSTAR":0.00032242094,"MEAN_MOTION_DOT":0.00024662,"MEAN_MOTION_DDOT":0},{"OBJECT_NAME":"ISS OBJECT XT","OBJECT_ID":"1998-067XT","EPOCH":"2026-04-11T19:29:00.303648","MEAN_MOTION":15.84614948,"ECCENTRICITY":0.00092944,"INCLINATION":51.6203,"RA_OF_ASC_NODE":255.0176,"ARG_OF_PERICENTER":295.1718,"MEAN_ANOMALY":64.8321,"EPHEMERIS_TYPE":0,"CLASSIFICATION_TYPE":"U","NORAD_CAT_ID":66907,"ELEMENT_SET_NO":999,"REV_AT_EPOCH":2040,"BSTAR":0.0011628372,"MEAN_MOTION_DOT":0.00283171,"MEAN_MOTION_DDOT":0},{"OBJECT_NAME":"ISS OBJECT XU","OBJECT_ID":"1998-067XU","EPOCH":"2026-04-12T02:52:52.415904","MEAN_MOTION":15.85236979,"ECCENTRICITY":0.000935,"INCLINATION":51.6199,"RA_OF_ASC_NODE":253.3197,"ARG_OF_PERICENTER":295.477,"MEAN_ANOMALY":64.5266,"EPHEMERIS_TYPE":0,"CLASSIFICATION_TYPE":"U","NORAD_CAT_ID":66908,"ELEMENT_SET_NO":999,"REV_AT_EPOCH":2045,"BSTAR":0.0011177943,"MEAN_MOTION_DOT":0.00280366,"MEAN_MOTION_DDOT":0},{"OBJECT_NAME":"SILVERSAT","OBJECT_ID":"1998-067XV","EPOCH":"2026-04-11T10:36:27.151488","MEAN_MOTION":15.95566356,"ECCENTRICITY":0.00119176,"INCLINATION":51.6155,"RA_OF_ASC_NODE":254.7584,"ARG_OF_PERICENTER":300.1845,"MEAN_ANOMALY":59.7981,"EPHEMERIS_TYPE":0,"CLASSIFICATION_TYPE":"U","NORAD_CAT_ID":66909,"ELEMENT_SET_NO":999,"REV_AT_EPOCH":2037,"BSTAR":0.0014302467,"MEAN_MOTION_DOT":0.00588813,"MEAN_MOTION_DDOT":0.00015492762},{"OBJECT_NAME":"ISS OBJECT XW","OBJECT_ID":"1998-067XW","EPOCH":"2026-04-11T17:03:55.343808","MEAN_MOTION":15.81724614,"ECCENTRICITY":0.00089198,"INCLINATION":51.6192,"RA_OF_ASC_NODE":255.8381,"ARG_OF_PERICENTER":287.8602,"MEAN_ANOMALY":72.1427,"EPHEMERIS_TYPE":0,"CLASSIFICATION_TYPE":"U","NORAD_CAT_ID":66910,"ELEMENT_SET_NO":999,"REV_AT_EPOCH":2038,"BSTAR":0.0012146166,"MEAN_MOTION_DOT":0.00257233,"MEAN_MOTION_DDOT":0},{"OBJECT_NAME":"ISS OBJECT XX","OBJECT_ID":"1998-067XX","EPOCH":"2026-04-11T10:59:50.563104","MEAN_MOTION":16.30633237,"ECCENTRICITY":0.00122036,"INCLINATION":51.599,"RA_OF_ASC_NODE":251.7761,"ARG_OF_PERICENTER":297.7475,"MEAN_ANOMALY":62.231,"EPHEMERIS_TYPE":0,"CLASSIFICATION_TYPE":"U","NORAD_CAT_ID":66911,"ELEMENT_SET_NO":999,"REV_AT_EPOCH":2040,"BSTAR":0.0013558254,"MEAN_MOTION_DOT":0.06931681,"MEAN_MOTION_DDOT":1.2208026e-5},{"OBJECT_NAME":"ISS OBJECT XY","OBJECT_ID":"1998-067XY","EPOCH":"2026-04-11T20:47:37.264992","MEAN_MOTION":15.71254778,"ECCENTRICITY":0.0005916,"INCLINATION":51.6241,"RA_OF_ASC_NODE":258.4264,"ARG_OF_PERICENTER":286.0307,"MEAN_ANOMALY":74.0039,"EPHEMERIS_TYPE":0,"CLASSIFICATION_TYPE":"U","NORAD_CAT_ID":66912,"ELEMENT_SET_NO":999,"REV_AT_EPOCH":2035,"BSTAR":0.00075975,"MEAN_MOTION_DOT":0.00098988,"MEAN_MOTION_DDOT":0},{"OBJECT_NAME":"KNACKSAT-2","OBJECT_ID":"1998-067XZ","EPOCH":"2026-04-11T20:41:09.760128","MEAN_MOTION":15.5471807,"ECCENTRICITY":0.00111054,"INCLINATION":51.6299,"RA_OF_ASC_NODE":266.6723,"ARG_OF_PERICENTER":310.2228,"MEAN_ANOMALY":49.779,"EPHEMERIS_TYPE":0,"CLASSIFICATION_TYPE":"U","NORAD_CAT_ID":67683,"ELEMENT_SET_NO":999,"REV_AT_EPOCH":994,"BSTAR":0.0004911856,"MEAN_MOTION_DOT":0.00032956,"MEAN_MOTION_DDOT":0},{"OBJECT_NAME":"CORAL","OBJECT_ID":"1998-067YA","EPOCH":"2026-04-11T17:59:03.285312","MEAN_MOTION":15.60463232,"ECCENTRICITY":0.00145732,"INCLINATION":51.6272,"RA_OF_ASC_NODE":265.9186,"ARG_OF_PERICENTER":301.4424,"MEAN_ANOMALY":58.5144,"EPHEMERIS_TYPE":0,"CLASSIFICATION_TYPE":"U","NORAD_CAT_ID":67684,"ELEMENT_SET_NO":999,"REV_AT_EPOCH":994,"BSTAR":0.001042626,"MEAN_MOTION_DOT":0.00088342,"MEAN_MOTION_DDOT":0},{"OBJECT_NAME":"GXIBA-1","OBJECT_ID":"1998-067YB","EPOCH":"2026-04-11T20:18:35.442720","MEAN_MOTION":15.55423821,"ECCENTRICITY":0.00130912,"INCLINATION":51.6298,"RA_OF_ASC_NODE":266.568,"ARG_OF_PERICENTER":307.251,"MEAN_ANOMALY":52.7287,"EPHEMERIS_TYPE":0,"CLASSIFICATION_TYPE":"U","NORAD_CAT_ID":67685,"ELEMENT_SET_NO":999,"REV_AT_EPOCH":994,"BSTAR":0.00051378235,"MEAN_MOTION_DOT":0.00035459,"MEAN_MOTION_DDOT":0},{"OBJECT_NAME":"UITMSAT-2","OBJECT_ID":"1998-067YC","EPOCH":"2026-04-11T04:18:19.418688","MEAN_MOTION":15.56684408,"ECCENTRICITY":0.00099952,"INCLINATION":51.6296,"RA_OF_ASC_NODE":269.6181,"ARG_OF_PERICENTER":281.9734,"MEAN_ANOMALY":78.0137,"EPHEMERIS_TYPE":0,"CLASSIFICATION_TYPE":"U","NORAD_CAT_ID":67686,"ELEMENT_SET_NO":999,"REV_AT_EPOCH":984,"BSTAR":0.00063790923,"MEAN_MOTION_DOT":0.00046265,"MEAN_MOTION_DDOT":0},{"OBJECT_NAME":"HMU-SAT2","OBJECT_ID":"1998-067YD","EPOCH":"2026-04-11T20:29:16.661184","MEAN_MOTION":15.55123718,"ECCENTRICITY":0.00096795,"INCLINATION":51.6319,"RA_OF_ASC_NODE":266.6219,"ARG_OF_PERICENTER":286.2702,"MEAN_ANOMALY":73.7224,"EPHEMERIS_TYPE":0,"CLASSIFICATION_TYPE":"U","NORAD_CAT_ID":67687,"ELEMENT_SET_NO":999,"REV_AT_EPOCH":986,"BSTAR":0.00053854973,"MEAN_MOTION_DOT":0.00036725,"MEAN_MOTION_DDOT":0},{"OBJECT_NAME":"LEOPARD","OBJECT_ID":"1998-067YE","EPOCH":"2026-04-11T18:26:36.712608","MEAN_MOTION":15.56141373,"ECCENTRICITY":0.00096099,"INCLINATION":51.6291,"RA_OF_ASC_NODE":266.8011,"ARG_OF_PERICENTER":284.4987,"MEAN_ANOMALY":75.4938,"EPHEMERIS_TYPE":0,"CLASSIFICATION_TYPE":"U","NORAD_CAT_ID":67688,"ELEMENT_SET_NO":999,"REV_AT_EPOCH":985,"BSTAR":0.00066276066,"MEAN_MOTION_DOT":0.00047117,"MEAN_MOTION_DDOT":0},{"OBJECT_NAME":"CREW DRAGON 12","OBJECT_ID":"2026-031A","EPOCH":"2026-04-11T22:35:02.626368","MEAN_MOTION":15.4887769,"ECCENTRICITY":0.00064516,"INCLINATION":51.6326,"RA_OF_ASC_NODE":267.9482,"ARG_OF_PERICENTER":301.5882,"MEAN_ANOMALY":58.4476,"EPHEMERIS_TYPE":0,"CLASSIFICATION_TYPE":"U","NORAD_CAT_ID":67796,"ELEMENT_SET_NO":999,"REV_AT_EPOCH":56150,"BSTAR":0.00010656761,"MEAN_MOTION_DOT":5.402e-5,"MEAN_MOTION_DDOT":0},{"OBJECT_NAME":"PROGRESS-MS 33","OBJECT_ID":"2026-058A","EPOCH":"2026-04-11T22:35:02.626368","MEAN_MOTION":15.4887769,"ECCENTRICITY":0.00064516,"INCLINATION":51.6326,"RA_OF_ASC_NODE":267.9482,"ARG_OF_PERICENTER":301.5882,"MEAN_ANOMALY":58.4476,"EPHEMERIS_TYPE":0,"CLASSIFICATION_TYPE":"U","NORAD_CAT_ID":68319,"ELEMENT_SET_NO":999,"REV_AT_EPOCH":224,"BSTAR":0.00010656761,"MEAN_MOTION_DOT":5.402e-5,"MEAN_MOTION_DDOT":0},{"OBJECT_NAME":"CYGNUS NG-24","OBJECT_ID":"2026-079A","EPOCH":"2026-04-12T06:59:40.312320","MEAN_MOTION":16.10282382,"ECCENTRICITY":0.00064639,"INCLINATION":51.6618,"RA_OF_ASC_NODE":266.5112,"ARG_OF_PERICENTER":290.6965,"MEAN_ANOMALY":69.3357,"EPHEMERIS_TYPE":0,"CLASSIFICATION_TYPE":"U","NORAD_CAT_ID":68689,"ELEMENT_SET_NO":999,"REV_AT_EPOCH":13,"BSTAR":0.00021455024,"MEAN_MOTION_DOT":0.0021007,"MEAN_MOTION_DDOT":3.2828943e-5}]
